odoo/addons/sale_invoice_policy/README.rst
odoo/addons/sale_invoice_policy/__init__.py
odoo/addons/sale_invoice_policy/__manifest__.py
odoo/addons/sale_invoice_policy/pre_init_hook.py
odoo/addons/sale_invoice_policy/i18n/ca.po
odoo/addons/sale_invoice_policy/i18n/es.po
odoo/addons/sale_invoice_policy/i18n/es_MX.po
odoo/addons/sale_invoice_policy/i18n/fr.po
odoo/addons/sale_invoice_policy/i18n/it.po
odoo/addons/sale_invoice_policy/i18n/pt.po
odoo/addons/sale_invoice_policy/i18n/sale_invoice_policy.pot
odoo/addons/sale_invoice_policy/models/__init__.py
odoo/addons/sale_invoice_policy/models/product_template.py
odoo/addons/sale_invoice_policy/models/sale_order.py
odoo/addons/sale_invoice_policy/models/sale_order_line.py
odoo/addons/sale_invoice_policy/readme/CONTRIBUTORS.rst
odoo/addons/sale_invoice_policy/readme/DESCRIPTION.rst
odoo/addons/sale_invoice_policy/readme/USAGE.rst
odoo/addons/sale_invoice_policy/static/description/icon.png
odoo/addons/sale_invoice_policy/static/description/index.html
odoo/addons/sale_invoice_policy/tests/__init__.py
odoo/addons/sale_invoice_policy/tests/test_sale_invoice_policy.py
odoo/addons/sale_invoice_policy/views/product_template_view.xml
odoo/addons/sale_invoice_policy/views/sale_view.xml
odoo14_addon_sale_invoice_policy-14.0.1.0.1.dev6.dist-info/METADATA
odoo14_addon_sale_invoice_policy-14.0.1.0.1.dev6.dist-info/WHEEL
odoo14_addon_sale_invoice_policy-14.0.1.0.1.dev6.dist-info/top_level.txt
odoo14_addon_sale_invoice_policy-14.0.1.0.1.dev6.dist-info/RECORD
